{
  "molssi_bse_schema": {
    "schema_type": "component",
    "schema_version": "0.1"
  },
  "description": "cc-pVQZ-F12_OPTRI",
  "data_source": "Original Basis Set Exchange",
  "elements": {
    "3": {
      "references": [
        "hill2010b"
      ],
      "electron_shells": [
        {
          "function_type": "gto",
          "region": "",
          "angular_momentum": [
            0
          ],
          "exponents": [
            "0.8451985"
          ],
          "coefficients": [
            [
              "1.0000000"
            ]
          ]
        },
        {
          "function_type": "gto",
          "region": "",
          "angular_momentum": [
            0
          ],
          "exponents": [
            "0.2488790"
          ],
          "coefficients": [
            [
              "1.0000000"
            ]
          ]
        },
        {
          "function_type": "gto",
          "region": "",
          "angular_momentum": [
            0
          ],
          "exponents": [
            "0.0646500"
          ],
          "coefficients": [
            [
              "1.0000000"
            ]
          ]
        },
        {
          "function_type": "gto",
          "region": "",
          "angular_momentum": [
            0
          ],
          "exponents": [
            "0.0301619"
          ],
          "coefficients": [
            [
              "1.0000000"
            ]
          ]
        },
        {
          "function_type": "gto",
          "region": "",
          "angular_momentum": [
            1
          ],
          "exponents": [
            "1.0857542"
          ],
          "coefficients": [
            [
              "1.0000000"
            ]
          ]
        },
        {
          "function_type": "gto",
          "region": "",
          "angular_momentum": [
            1
          ],
          "exponents": [
            "0.2297834"
          ],
          "coefficients": [
            [
              "1.0000000"
            ]
          ]
        },
        {
          "function_type": "gto",
          "region": "",
          "angular_momentum": [
            1
          ],
          "exponents": [
            "0.1095952"
          ],
          "coefficients": [
            [
              "1.0000000"
            ]
          ]
        },
        {
          "function_type": "gto",
          "region": "",
          "angular_momentum": [
            1
          ],
          "exponents": [
            "0.0443739"
          ],
          "coefficients": [
            [
              "1.0000000"
            ]
          ]
        },
        {
          "function_type": "gto_spherical",
          "region": "",
          "angular_momentum": [
            2
          ],
          "exponents": [
            "2.5069256"
          ],
          "coefficients": [
            [
              "1.0000000"
            ]
          ]
        },
        {
          "function_type": "gto_spherical",
          "region": "",
          "angular_momentum": [
            2
          ],
          "exponents": [
            "1.2189964"
          ],
          "coefficients": [
            [
              "1.0000000"
            ]
          ]
        },
        {
          "function_type": "gto_spherical",
          "region": "",
          "angular_momentum": [
            2
          ],
          "exponents": [
            "0.6375434"
          ],
          "coefficients": [
            [
              "1.0000000"
            ]
          ]
        },
        {
          "function_type": "gto_spherical",
          "region": "",
          "angular_momentum": [
            2
          ],
          "exponents": [
            "0.0694315"
          ],
          "coefficients": [
            [
              "1.0000000"
            ]
          ]
        },
        {
          "function_type": "gto_spherical",
          "region": "",
          "angular_momentum": [
            3
          ],
          "exponents": [
            "0.6821848"
          ],
          "coefficients": [
            [
              "1.0000000"
            ]
          ]
        },
        {
          "function_type": "gto_spherical",
          "region": "",
          "angular_momentum": [
            3
          ],
          "exponents": [
            "0.2698737"
          ],
          "coefficients": [
            [
              "1.0000000"
            ]
          ]
        },
        {
          "function_type": "gto_spherical",
          "region": "",
          "angular_momentum": [
            3
          ],
          "exponents": [
            "0.0543696"
          ],
          "coefficients": [
            [
              "1.0000000"
            ]
          ]
        },
        {
          "function_type": "gto_spherical",
          "region": "",
          "angular_momentum": [
            4
          ],
          "exponents": [
            "0.7895759"
          ],
          "coefficients": [
            [
              "1.0000000"
            ]
          ]
        },
        {
          "function_type": "gto_spherical",
          "region": "",
          "angular_momentum": [
            4
          ],
          "exponents": [
            "0.2548198"
          ],
          "coefficients": [
            [
              "1.0000000"
            ]
          ]
        },
        {
          "function_type": "gto_spherical",
          "region": "",
          "angular_momentum": [
            5
          ],
          "exponents": [
            "0.2146354"
          ],
          "coefficients": [
            [
              "1.0000000"
            ]
          ]
        }
      ]
    },
    "4": {
      "references": [
        "hill2010b"
      ],
      "electron_shells": [
        {
          "function_type": "gto",
          "region": "",
          "angular_momentum": [
            0
          ],
          "exponents": [
            "1.1538476"
          ],
          "coefficients": [
            [
              "1.0000000"
            ]
          ]
        },
        {
          "function_type": "gto",
          "region": "",
          "angular_momentum": [
            0
          ],
          "exponents": [
            "0.6789828"
          ],
          "coefficients": [
            [
              "1.0000000"
            ]
          ]
        },
        {
          "function_type": "gto",
          "region": "",
          "angular_momentum": [
            0
          ],
          "exponents": [
            "0.1464629"
          ],
          "coefficients": [
            [
              "1.0000000"
            ]
          ]
        },
        {
          "function_type": "gto",
          "region": "",
          "angular_momentum": [
            0
          ],
          "exponents": [
            "0.0759645"
          ],
          "coefficients": [
            [
              "1.0000000"
            ]
          ]
        },
        {
          "function_type": "gto",
          "region": "",
          "angular_momentum": [
            1
          ],
          "exponents": [
            "2.6789666"
          ],
          "coefficients": [
            [
              "1.0000000"
            ]
          ]
        },
        {
          "function_type": "gto",
          "region": "",
          "angular_momentum": [
            1
          ],
          "exponents": [
            "0.8663593"
          ],
          "coefficients": [
            [
              "1.0000000"
            ]
          ]
        },
        {
          "function_type": "gto",
          "region": "",
          "angular_momentum": [
            1
          ],
          "exponents": [
            "0.3320433"
          ],
          "coefficients": [
            [
              "1.0000000"
            ]
          ]
        },
        {
          "function_type": "gto",
          "region": "",
          "angular_momentum": [
            1
          ],
          "exponents": [
            "0.1371140"
          ],
          "coefficients": [
            [
              "1.0000000"
            ]
          ]
        },
        {
          "function_type": "gto_spherical",
          "region": "",
          "angular_momentum": [
            2
          ],
          "exponents": [
            "3.3831501"
          ],
          "coefficients": [
            [
              "1.0000000"
            ]
          ]
        },
        {
          "function_type": "gto_spherical",
          "region": "",
          "angular_momentum": [
            2
          ],
          "exponents": [
            "0.6313387"
          ],
          "coefficients": [
            [
              "1.0000000"
            ]
          ]
        },
        {
          "function_type": "gto_spherical",
          "region": "",
          "angular_momentum": [
            2
          ],
          "exponents": [
            "0.3584863"
          ],
          "coefficients": [
            [
              "1.0000000"
            ]
          ]
        },
        {
          "function_type": "gto_spherical",
          "region": "",
          "angular_momentum": [
            2
          ],
          "exponents": [
            "0.1529038"
          ],
          "coefficients": [
            [
              "1.0000000"
            ]
          ]
        },
        {
          "function_type": "gto_spherical",
          "region": "",
          "angular_momentum": [
            3
          ],
          "exponents": [
            "1.5661094"
          ],
          "coefficients": [
            [
              "1.0000000"
            ]
          ]
        },
        {
          "function_type": "gto_spherical",
          "region": "",
          "angular_momentum": [
            3
          ],
          "exponents": [
            "0.8580755"
          ],
          "coefficients": [
            [
              "1.0000000"
            ]
          ]
        },
        {
          "function_type": "gto_spherical",
          "region": "",
          "angular_momentum": [
            3
          ],
          "exponents": [
            "0.3125031"
          ],
          "coefficients": [
            [
              "1.0000000"
            ]
          ]
        },
        {
          "function_type": "gto_spherical",
          "region": "",
          "angular_momentum": [
            4
          ],
          "exponents": [
            "0.4468738"
          ],
          "coefficients": [
            [
              "1.0000000"
            ]
          ]
        },
        {
          "function_type": "gto_spherical",
          "region": "",
          "angular_momentum": [
            4
          ],
          "exponents": [
            "0.2180355"
          ],
          "coefficients": [
            [
              "1.0000000"
            ]
          ]
        },
        {
          "function_type": "gto_spherical",
          "region": "",
          "angular_momentum": [
            5
          ],
          "exponents": [
            "0.4737481"
          ],
          "coefficients": [
            [
              "1.0000000"
            ]
          ]
        }
      ]
    },
    "11": {
      "references": [
        "hill2010b"
      ],
      "electron_shells": [
        {
          "function_type": "gto",
          "region": "",
          "angular_momentum": [
            0
          ],
          "exponents": [
            "0.9707935"
          ],
          "coefficients": [
            [
              "1.0000000"
            ]
          ]
        },
        {
          "function_type": "gto",
          "region": "",
          "angular_momentum": [
            0
          ],
          "exponents": [
            "0.2642263"
          ],
          "coefficients": [
            [
              "1.0000000"
            ]
          ]
        },
        {
          "function_type": "gto",
          "region": "",
          "angular_momentum": [
            0
          ],
          "exponents": [
            "0.0545049"
          ],
          "coefficients": [
            [
              "1.0000000"
            ]
          ]
        },
        {
          "function_type": "gto",
          "region": "",
          "angular_momentum": [
            0
          ],
          "exponents": [
            "0.0260137"
          ],
          "coefficients": [
            [
              "1.0000000"
            ]
          ]
        },
        {
          "function_type": "gto",
          "region": "",
          "angular_momentum": [
            1
          ],
          "exponents": [
            "0.9788400"
          ],
          "coefficients": [
            [
              "1.0000000"
            ]
          ]
        },
        {
          "function_type": "gto",
          "region": "",
          "angular_momentum": [
            1
          ],
          "exponents": [
            "0.4001723"
          ],
          "coefficients": [
            [
              "1.0000000"
            ]
          ]
        },
        {
          "function_type": "gto",
          "region": "",
          "angular_momentum": [
            1
          ],
          "exponents": [
            "0.1745833"
          ],
          "coefficients": [
            [
              "1.0000000"
            ]
          ]
        },
        {
          "function_type": "gto",
          "region": "",
          "angular_momentum": [
            1
          ],
          "exponents": [
            "0.0771366"
          ],
          "coefficients": [
            [
              "1.0000000"
            ]
          ]
        },
        {
          "function_type": "gto_spherical",
          "region": "",
          "angular_momentum": [
            2
          ],
          "exponents": [
            "6.8189293"
          ],
          "coefficients": [
            [
              "1.0000000"
            ]
          ]
        },
        {
          "function_type": "gto_spherical",
          "region": "",
          "angular_momentum": [
            2
          ],
          "exponents": [
            "1.1646110"
          ],
          "coefficients": [
            [
              "1.0000000"
            ]
          ]
        },
        {
          "function_type": "gto_spherical",
          "region": "",
          "angular_momentum": [
            2
          ],
          "exponents": [
            "0.7472029"
          ],
          "coefficients": [
            [
              "1.0000000"
            ]
          ]
        },
        {
          "function_type": "gto_spherical",
          "region": "",
          "angular_momentum": [
            2
          ],
          "exponents": [
            "0.1779187"
          ],
          "coefficients": [
            [
              "1.0000000"
            ]
          ]
        },
        {
          "function_type": "gto_spherical",
          "region": "",
          "angular_momentum": [
            3
          ],
          "exponents": [
            "0.7656361"
          ],
          "coefficients": [
            [
              "1.0000000"
            ]
          ]
        },
        {
          "function_type": "gto_spherical",
          "region": "",
          "angular_momentum": [
            3
          ],
          "exponents": [
            "0.2363150"
          ],
          "coefficients": [
            [
              "1.0000000"
            ]
          ]
        },
        {
          "function_type": "gto_spherical",
          "region": "",
          "angular_momentum": [
            3
          ],
          "exponents": [
            "0.1406358"
          ],
          "coefficients": [
            [
              "1.0000000"
            ]
          ]
        },
        {
          "function_type": "gto_spherical",
          "region": "",
          "angular_momentum": [
            4
          ],
          "exponents": [
            "0.2680699"
          ],
          "coefficients": [
            [
              "1.0000000"
            ]
          ]
        },
        {
          "function_type": "gto_spherical",
          "region": "",
          "angular_momentum": [
            4
          ],
          "exponents": [
            "0.2056775"
          ],
          "coefficients": [
            [
              "1.0000000"
            ]
          ]
        },
        {
          "function_type": "gto_spherical",
          "region": "",
          "angular_momentum": [
            5
          ],
          "exponents": [
            "0.0919160"
          ],
          "coefficients": [
            [
              "1.0000000"
            ]
          ]
        }
      ]
    },
    "12": {
      "references": [
        "hill2010b"
      ],
      "electron_shells": [
        {
          "function_type": "gto",
          "region": "",
          "angular_momentum": [
            0
          ],
          "exponents": [
            "1.3130881"
          ],
          "coefficients": [
            [
              "1.0000000"
            ]
          ]
        },
        {
          "function_type": "gto",
          "region": "",
          "angular_momentum": [
            0
          ],
          "exponents": [
            "0.2607942"
          ],
          "coefficients": [
            [
              "1.0000000"
            ]
          ]
        },
        {
          "function_type": "gto",
          "region": "",
          "angular_momentum": [
            0
          ],
          "exponents": [
            "0.1002906"
          ],
          "coefficients": [
            [
              "1.0000000"
            ]
          ]
        },
        {
          "function_type": "gto",
          "region": "",
          "angular_momentum": [
            0
          ],
          "exponents": [
            "0.0487505"
          ],
          "coefficients": [
            [
              "1.0000000"
            ]
          ]
        },
        {
          "function_type": "gto",
          "region": "",
          "angular_momentum": [
            1
          ],
          "exponents": [
            "1.0245929"
          ],
          "coefficients": [
            [
              "1.0000000"
            ]
          ]
        },
        {
          "function_type": "gto",
          "region": "",
          "angular_momentum": [
            1
          ],
          "exponents": [
            "0.2322582"
          ],
          "coefficients": [
            [
              "1.0000000"
            ]
          ]
        },
        {
          "function_type": "gto",
          "region": "",
          "angular_momentum": [
            1
          ],
          "exponents": [
            "0.1218831"
          ],
          "coefficients": [
            [
              "1.0000000"
            ]
          ]
        },
        {
          "function_type": "gto",
          "region": "",
          "angular_momentum": [
            1
          ],
          "exponents": [
            "0.0629715"
          ],
          "coefficients": [
            [
              "1.0000000"
            ]
          ]
        },
        {
          "function_type": "gto_spherical",
          "region": "",
          "angular_momentum": [
            2
          ],
          "exponents": [
            "3.9988663"
          ],
          "coefficients": [
            [
              "1.0000000"
            ]
          ]
        },
        {
          "function_type": "gto_spherical",
          "region": "",
          "angular_momentum": [
            2
          ],
          "exponents": [
            "1.1973808"
          ],
          "coefficients": [
            [
              "1.0000000"
            ]
          ]
        },
        {
          "function_type": "gto_spherical",
          "region": "",
          "angular_momentum": [
            2
          ],
          "exponents": [
            "0.2727999"
          ],
          "coefficients": [
            [
              "1.0000000"
            ]
          ]
        },
        {
          "function_type": "gto_spherical",
          "region": "",
          "angular_momentum": [
            2
          ],
          "exponents": [
            "0.1527236"
          ],
          "coefficients": [
            [
              "1.0000000"
            ]
          ]
        },
        {
          "function_type": "gto_spherical",
          "region": "",
          "angular_momentum": [
            3
          ],
          "exponents": [
            "1.6372414"
          ],
          "coefficients": [
            [
              "1.0000000"
            ]
          ]
        },
        {
          "function_type": "gto_spherical",
          "region": "",
          "angular_momentum": [
            3
          ],
          "exponents": [
            "0.6931314"
          ],
          "coefficients": [
            [
              "1.0000000"
            ]
          ]
        },
        {
          "function_type": "gto_spherical",
          "region": "",
          "angular_momentum": [
            3
          ],
          "exponents": [
            "0.2326890"
          ],
          "coefficients": [
            [
              "1.0000000"
            ]
          ]
        },
        {
          "function_type": "gto_spherical",
          "region": "",
          "angular_momentum": [
            4
          ],
          "exponents": [
            "0.6677045"
          ],
          "coefficients": [
            [
              "1.0000000"
            ]
          ]
        },
        {
          "function_type": "gto_spherical",
          "region": "",
          "angular_momentum": [
            4
          ],
          "exponents": [
            "0.5124749"
          ],
          "coefficients": [
            [
              "1.0000000"
            ]
          ]
        },
        {
          "function_type": "gto_spherical",
          "region": "",
          "angular_momentum": [
            5
          ],
          "exponents": [
            "0.1189690"
          ],
          "coefficients": [
            [
              "1.0000000"
            ]
          ]
        }
      ]
    }
  }
}