{
    "molssi_bse_schema": {
        "schema_type": "component",
        "schema_version": "0.1"
    },
    "basis_set_description": "DZPD    Double Zeta + Polarization + Diffuse",
    "basis_set_references": [
        "CHIPMAN-BS-REF"
    ],
    "basis_set_elements": {
        "1": {
            "element_electron_shells": [
                {
                    "shell_function_type": "gto",
                    "shell_harmonic_type": "spherical",
                    "shell_region": "",
                    "shell_angular_momentum": [
                        0
                    ],
                    "shell_exponents": [
                        "127.950",
                        "19.2406",
                        "2.89920"
                    ],
                    "shell_coefficients": [
                        [
                            "0.010736",
                            "0.119544",
                            "0.926416"
                        ]
                    ]
                },
                {
                    "shell_function_type": "gto",
                    "shell_harmonic_type": "spherical",
                    "shell_region": "",
                    "shell_angular_momentum": [
                        0
                    ],
                    "shell_exponents": [
                        "0.65340"
                    ],
                    "shell_coefficients": [
                        [
                            "1.000000"
                        ]
                    ]
                },
                {
                    "shell_function_type": "gto",
                    "shell_harmonic_type": "spherical",
                    "shell_region": "",
                    "shell_angular_momentum": [
                        0
                    ],
                    "shell_exponents": [
                        "0.17760"
                    ],
                    "shell_coefficients": [
                        [
                            "1.000000"
                        ]
                    ]
                },
                {
                    "shell_function_type": "gto",
                    "shell_harmonic_type": "spherical",
                    "shell_region": "",
                    "shell_angular_momentum": [
                        0
                    ],
                    "shell_exponents": [
                        "0.04830"
                    ],
                    "shell_coefficients": [
                        [
                            "1.000000"
                        ]
                    ]
                },
                {
                    "shell_function_type": "gto",
                    "shell_harmonic_type": "spherical",
                    "shell_region": "",
                    "shell_angular_momentum": [
                        1
                    ],
                    "shell_exponents": [
                        "1.00000"
                    ],
                    "shell_coefficients": [
                        [
                            "1.000000"
                        ]
                    ]
                }
            ]
        },
        "5": {
            "element_electron_shells": [
                {
                    "shell_function_type": "gto",
                    "shell_harmonic_type": "spherical",
                    "shell_region": "",
                    "shell_angular_momentum": [
                        0
                    ],
                    "shell_exponents": [
                        "2788.41",
                        "419.039",
                        "96.4683",
                        "28.0694",
                        "9.37600"
                    ],
                    "shell_coefficients": [
                        [
                            "0.002122",
                            "0.016171",
                            "0.078356",
                            "0.263250",
                            "0.596729"
                        ]
                    ]
                },
                {
                    "shell_function_type": "gto",
                    "shell_harmonic_type": "spherical",
                    "shell_region": "",
                    "shell_angular_momentum": [
                        0
                    ],
                    "shell_exponents": [
                        "1.30570"
                    ],
                    "shell_coefficients": [
                        [
                            "1.000000"
                        ]
                    ]
                },
                {
                    "shell_function_type": "gto",
                    "shell_harmonic_type": "spherical",
                    "shell_region": "",
                    "shell_angular_momentum": [
                        0
                    ],
                    "shell_exponents": [
                        "3.40620"
                    ],
                    "shell_coefficients": [
                        [
                            "1.000000"
                        ]
                    ]
                },
                {
                    "shell_function_type": "gto",
                    "shell_harmonic_type": "spherical",
                    "shell_region": "",
                    "shell_angular_momentum": [
                        0
                    ],
                    "shell_exponents": [
                        "0.3245"
                    ],
                    "shell_coefficients": [
                        [
                            "1.000000"
                        ]
                    ]
                },
                {
                    "shell_function_type": "gto",
                    "shell_harmonic_type": "spherical",
                    "shell_region": "",
                    "shell_angular_momentum": [
                        0
                    ],
                    "shell_exponents": [
                        "0.1022"
                    ],
                    "shell_coefficients": [
                        [
                            "1.000000"
                        ]
                    ]
                },
                {
                    "shell_function_type": "gto",
                    "shell_harmonic_type": "spherical",
                    "shell_region": "",
                    "shell_angular_momentum": [
                        0
                    ],
                    "shell_exponents": [
                        "0.0330"
                    ],
                    "shell_coefficients": [
                        [
                            "1.000000"
                        ]
                    ]
                },
                {
                    "shell_function_type": "gto",
                    "shell_harmonic_type": "spherical",
                    "shell_region": "",
                    "shell_angular_momentum": [
                        1
                    ],
                    "shell_exponents": [
                        "11.3413",
                        "2.43600",
                        "0.68360",
                        "0.21340"
                    ],
                    "shell_coefficients": [
                        [
                            "0.017987",
                            "0.110339",
                            "0.383111",
                            "0.647860"
                        ]
                    ]
                },
                {
                    "shell_function_type": "gto",
                    "shell_harmonic_type": "spherical",
                    "shell_region": "",
                    "shell_angular_momentum": [
                        1
                    ],
                    "shell_exponents": [
                        "0.07010"
                    ],
                    "shell_coefficients": [
                        [
                            "1.000000"
                        ]
                    ]
                },
                {
                    "shell_function_type": "gto",
                    "shell_harmonic_type": "spherical",
                    "shell_region": "",
                    "shell_angular_momentum": [
                        1
                    ],
                    "shell_exponents": [
                        "0.02260"
                    ],
                    "shell_coefficients": [
                        [
                            "1.000000"
                        ]
                    ]
                },
                {
                    "shell_function_type": "gto",
                    "shell_harmonic_type": "spherical",
                    "shell_region": "",
                    "shell_angular_momentum": [
                        2
                    ],
                    "shell_exponents": [
                        "0.16000"
                    ],
                    "shell_coefficients": [
                        [
                            "1.000000"
                        ]
                    ]
                },
                {
                    "shell_function_type": "gto",
                    "shell_harmonic_type": "spherical",
                    "shell_region": "",
                    "shell_angular_momentum": [
                        2
                    ],
                    "shell_exponents": [
                        "0.64000"
                    ],
                    "shell_coefficients": [
                        [
                            "1.000000"
                        ]
                    ]
                }
            ]
        },
        "6": {
            "element_electron_shells": [
                {
                    "shell_function_type": "gto",
                    "shell_harmonic_type": "spherical",
                    "shell_region": "",
                    "shell_angular_momentum": [
                        0
                    ],
                    "shell_exponents": [
                        "4232.61",
                        "634.882",
                        "146.097",
                        "42.4974",
                        "14.1892"
                    ],
                    "shell_coefficients": [
                        [
                            "0.002029",
                            "0.015535",
                            "0.075411",
                            "0.257121",
                            "0.596555"
                        ]
                    ]
                },
                {
                    "shell_function_type": "gto",
                    "shell_harmonic_type": "spherical",
                    "shell_region": "",
                    "shell_angular_momentum": [
                        0
                    ],
                    "shell_exponents": [
                        "1.96660"
                    ],
                    "shell_coefficients": [
                        [
                            "1.000000"
                        ]
                    ]
                },
                {
                    "shell_function_type": "gto",
                    "shell_harmonic_type": "spherical",
                    "shell_region": "",
                    "shell_angular_momentum": [
                        0
                    ],
                    "shell_exponents": [
                        "5.14770"
                    ],
                    "shell_coefficients": [
                        [
                            "1.000000"
                        ]
                    ]
                },
                {
                    "shell_function_type": "gto",
                    "shell_harmonic_type": "spherical",
                    "shell_region": "",
                    "shell_angular_momentum": [
                        0
                    ],
                    "shell_exponents": [
                        "0.4962"
                    ],
                    "shell_coefficients": [
                        [
                            "1.000000"
                        ]
                    ]
                },
                {
                    "shell_function_type": "gto",
                    "shell_harmonic_type": "spherical",
                    "shell_region": "",
                    "shell_angular_momentum": [
                        0
                    ],
                    "shell_exponents": [
                        "0.1533"
                    ],
                    "shell_coefficients": [
                        [
                            "1.000000"
                        ]
                    ]
                },
                {
                    "shell_function_type": "gto",
                    "shell_harmonic_type": "spherical",
                    "shell_region": "",
                    "shell_angular_momentum": [
                        0
                    ],
                    "shell_exponents": [
                        "0.0479"
                    ],
                    "shell_coefficients": [
                        [
                            "1.000000"
                        ]
                    ]
                },
                {
                    "shell_function_type": "gto",
                    "shell_harmonic_type": "spherical",
                    "shell_region": "",
                    "shell_angular_momentum": [
                        1
                    ],
                    "shell_exponents": [
                        "18.1557",
                        "3.98640",
                        "1.14290",
                        "0.35940"
                    ],
                    "shell_coefficients": [
                        [
                            "0.018534",
                            "0.115442",
                            "0.386206",
                            "0.640089"
                        ]
                    ]
                },
                {
                    "shell_function_type": "gto",
                    "shell_harmonic_type": "spherical",
                    "shell_region": "",
                    "shell_angular_momentum": [
                        1
                    ],
                    "shell_exponents": [
                        "0.11460"
                    ],
                    "shell_coefficients": [
                        [
                            "1.000000"
                        ]
                    ]
                },
                {
                    "shell_function_type": "gto",
                    "shell_harmonic_type": "spherical",
                    "shell_region": "",
                    "shell_angular_momentum": [
                        1
                    ],
                    "shell_exponents": [
                        "0.03580"
                    ],
                    "shell_coefficients": [
                        [
                            "1.000000"
                        ]
                    ]
                },
                {
                    "shell_function_type": "gto",
                    "shell_harmonic_type": "spherical",
                    "shell_region": "",
                    "shell_angular_momentum": [
                        2
                    ],
                    "shell_exponents": [
                        "0.28000"
                    ],
                    "shell_coefficients": [
                        [
                            "1.000000"
                        ]
                    ]
                },
                {
                    "shell_function_type": "gto",
                    "shell_harmonic_type": "spherical",
                    "shell_region": "",
                    "shell_angular_momentum": [
                        2
                    ],
                    "shell_exponents": [
                        "1.12000"
                    ],
                    "shell_coefficients": [
                        [
                            "1.000000"
                        ]
                    ]
                }
            ]
        },
        "7": {
            "element_electron_shells": [
                {
                    "shell_function_type": "gto",
                    "shell_harmonic_type": "spherical",
                    "shell_region": "",
                    "shell_angular_momentum": [
                        0
                    ],
                    "shell_exponents": [
                        "5909.44",
                        "887.451",
                        "204.749",
                        "59.8376",
                        "19.9981"
                    ],
                    "shell_coefficients": [
                        [
                            "0.002004",
                            "0.015310",
                            "0.074293",
                            "0.253364",
                            "0.600576"
                        ]
                    ]
                },
                {
                    "shell_function_type": "gto",
                    "shell_harmonic_type": "spherical",
                    "shell_region": "",
                    "shell_angular_momentum": [
                        0
                    ],
                    "shell_exponents": [
                        "2.6860"
                    ],
                    "shell_coefficients": [
                        [
                            "1.000000"
                        ]
                    ]
                },
                {
                    "shell_function_type": "gto",
                    "shell_harmonic_type": "spherical",
                    "shell_region": "",
                    "shell_angular_momentum": [
                        0
                    ],
                    "shell_exponents": [
                        "7.1927"
                    ],
                    "shell_coefficients": [
                        [
                            "1.000000"
                        ]
                    ]
                },
                {
                    "shell_function_type": "gto",
                    "shell_harmonic_type": "spherical",
                    "shell_region": "",
                    "shell_angular_momentum": [
                        0
                    ],
                    "shell_exponents": [
                        "0.7000"
                    ],
                    "shell_coefficients": [
                        [
                            "1.000000"
                        ]
                    ]
                },
                {
                    "shell_function_type": "gto",
                    "shell_harmonic_type": "spherical",
                    "shell_region": "",
                    "shell_angular_momentum": [
                        0
                    ],
                    "shell_exponents": [
                        "0.2133"
                    ],
                    "shell_coefficients": [
                        [
                            "1.000000"
                        ]
                    ]
                },
                {
                    "shell_function_type": "gto",
                    "shell_harmonic_type": "spherical",
                    "shell_region": "",
                    "shell_angular_momentum": [
                        0
                    ],
                    "shell_exponents": [
                        "0.0667"
                    ],
                    "shell_coefficients": [
                        [
                            "1.000000"
                        ]
                    ]
                },
                {
                    "shell_function_type": "gto",
                    "shell_harmonic_type": "spherical",
                    "shell_region": "",
                    "shell_angular_momentum": [
                        1
                    ],
                    "shell_exponents": [
                        "26.786",
                        "5.9564",
                        "1.7074",
                        "0.5314"
                    ],
                    "shell_coefficients": [
                        [
                            "0.018257",
                            "0.116407",
                            "0.390111",
                            "0.637221"
                        ]
                    ]
                },
                {
                    "shell_function_type": "gto",
                    "shell_harmonic_type": "spherical",
                    "shell_region": "",
                    "shell_angular_momentum": [
                        1
                    ],
                    "shell_exponents": [
                        "0.1654"
                    ],
                    "shell_coefficients": [
                        [
                            "1.000000"
                        ]
                    ]
                },
                {
                    "shell_function_type": "gto",
                    "shell_harmonic_type": "spherical",
                    "shell_region": "",
                    "shell_angular_momentum": [
                        1
                    ],
                    "shell_exponents": [
                        "0.0517"
                    ],
                    "shell_coefficients": [
                        [
                            "1.000000"
                        ]
                    ]
                },
                {
                    "shell_function_type": "gto",
                    "shell_harmonic_type": "spherical",
                    "shell_region": "",
                    "shell_angular_momentum": [
                        2
                    ],
                    "shell_exponents": [
                        "0.37000"
                    ],
                    "shell_coefficients": [
                        [
                            "1.000000"
                        ]
                    ]
                },
                {
                    "shell_function_type": "gto",
                    "shell_harmonic_type": "spherical",
                    "shell_region": "",
                    "shell_angular_momentum": [
                        2
                    ],
                    "shell_exponents": [
                        "1.48000"
                    ],
                    "shell_coefficients": [
                        [
                            "1.000000"
                        ]
                    ]
                }
            ]
        },
        "8": {
            "element_electron_shells": [
                {
                    "shell_function_type": "gto",
                    "shell_harmonic_type": "spherical",
                    "shell_region": "",
                    "shell_angular_momentum": [
                        0
                    ],
                    "shell_exponents": [
                        "7816.54",
                        "1175.82",
                        "273.188",
                        "81.1696",
                        "27.1836"
                    ],
                    "shell_coefficients": [
                        [
                            "0.002031",
                            "0.015436",
                            "0.073771",
                            "0.247606",
                            "0.611832"
                        ]
                    ]
                },
                {
                    "shell_function_type": "gto",
                    "shell_harmonic_type": "spherical",
                    "shell_region": "",
                    "shell_angular_momentum": [
                        0
                    ],
                    "shell_exponents": [
                        "3.41360"
                    ],
                    "shell_coefficients": [
                        [
                            "1.000000"
                        ]
                    ]
                },
                {
                    "shell_function_type": "gto",
                    "shell_harmonic_type": "spherical",
                    "shell_region": "",
                    "shell_angular_momentum": [
                        0
                    ],
                    "shell_exponents": [
                        "9.5322"
                    ],
                    "shell_coefficients": [
                        [
                            "1.000000"
                        ]
                    ]
                },
                {
                    "shell_function_type": "gto",
                    "shell_harmonic_type": "spherical",
                    "shell_region": "",
                    "shell_angular_momentum": [
                        0
                    ],
                    "shell_exponents": [
                        "0.9398"
                    ],
                    "shell_coefficients": [
                        [
                            "1.000000"
                        ]
                    ]
                },
                {
                    "shell_function_type": "gto",
                    "shell_harmonic_type": "spherical",
                    "shell_region": "",
                    "shell_angular_momentum": [
                        0
                    ],
                    "shell_exponents": [
                        "0.2846"
                    ],
                    "shell_coefficients": [
                        [
                            "1.000000"
                        ]
                    ]
                },
                {
                    "shell_function_type": "gto",
                    "shell_harmonic_type": "spherical",
                    "shell_region": "",
                    "shell_angular_momentum": [
                        0
                    ],
                    "shell_exponents": [
                        "0.0862"
                    ],
                    "shell_coefficients": [
                        [
                            "1.000000"
                        ]
                    ]
                },
                {
                    "shell_function_type": "gto",
                    "shell_harmonic_type": "spherical",
                    "shell_region": "",
                    "shell_angular_momentum": [
                        1
                    ],
                    "shell_exponents": [
                        "35.1832",
                        "7.9040",
                        "2.3051",
                        "0.7171"
                    ],
                    "shell_coefficients": [
                        [
                            "0.019580",
                            "0.124189",
                            "0.394727",
                            "0.627375"
                        ]
                    ]
                },
                {
                    "shell_function_type": "gto",
                    "shell_harmonic_type": "spherical",
                    "shell_region": "",
                    "shell_angular_momentum": [
                        1
                    ],
                    "shell_exponents": [
                        "0.2137"
                    ],
                    "shell_coefficients": [
                        [
                            "1.000000"
                        ]
                    ]
                },
                {
                    "shell_function_type": "gto",
                    "shell_harmonic_type": "spherical",
                    "shell_region": "",
                    "shell_angular_momentum": [
                        1
                    ],
                    "shell_exponents": [
                        "0.0648"
                    ],
                    "shell_coefficients": [
                        [
                            "1.000000"
                        ]
                    ]
                },
                {
                    "shell_function_type": "gto",
                    "shell_harmonic_type": "spherical",
                    "shell_region": "",
                    "shell_angular_momentum": [
                        2
                    ],
                    "shell_exponents": [
                        "0.55000"
                    ],
                    "shell_coefficients": [
                        [
                            "1.000000"
                        ]
                    ]
                },
                {
                    "shell_function_type": "gto",
                    "shell_harmonic_type": "spherical",
                    "shell_region": "",
                    "shell_angular_momentum": [
                        2
                    ],
                    "shell_exponents": [
                        "2.20000"
                    ],
                    "shell_coefficients": [
                        [
                            "1.000000"
                        ]
                    ]
                }
            ]
        },
        "9": {
            "element_electron_shells": [
                {
                    "shell_function_type": "gto",
                    "shell_harmonic_type": "spherical",
                    "shell_region": "",
                    "shell_angular_momentum": [
                        0
                    ],
                    "shell_exponents": [
                        "9994.79",
                        "1506.03",
                        "350.269",
                        "104.053",
                        "34.8432"
                    ],
                    "shell_coefficients": [
                        [
                            "0.002017",
                            "0.015295",
                            "0.073110",
                            "0.246420",
                            "0.612593"
                        ]
                    ]
                },
                {
                    "shell_function_type": "gto",
                    "shell_harmonic_type": "spherical",
                    "shell_region": "",
                    "shell_angular_momentum": [
                        0
                    ],
                    "shell_exponents": [
                        "4.36880"
                    ],
                    "shell_coefficients": [
                        [
                            "1.000000"
                        ]
                    ]
                },
                {
                    "shell_function_type": "gto",
                    "shell_harmonic_type": "spherical",
                    "shell_region": "",
                    "shell_angular_momentum": [
                        0
                    ],
                    "shell_exponents": [
                        "12.2164"
                    ],
                    "shell_coefficients": [
                        [
                            "1.000000"
                        ]
                    ]
                },
                {
                    "shell_function_type": "gto",
                    "shell_harmonic_type": "spherical",
                    "shell_region": "",
                    "shell_angular_momentum": [
                        0
                    ],
                    "shell_exponents": [
                        "1.2078"
                    ],
                    "shell_coefficients": [
                        [
                            "1.000000"
                        ]
                    ]
                },
                {
                    "shell_function_type": "gto",
                    "shell_harmonic_type": "spherical",
                    "shell_region": "",
                    "shell_angular_momentum": [
                        0
                    ],
                    "shell_exponents": [
                        "0.3634"
                    ],
                    "shell_coefficients": [
                        [
                            "1.000000"
                        ]
                    ]
                },
                {
                    "shell_function_type": "gto",
                    "shell_harmonic_type": "spherical",
                    "shell_region": "",
                    "shell_angular_momentum": [
                        0
                    ],
                    "shell_exponents": [
                        "0.1101"
                    ],
                    "shell_coefficients": [
                        [
                            "1.000000"
                        ]
                    ]
                },
                {
                    "shell_function_type": "gto",
                    "shell_harmonic_type": "spherical",
                    "shell_region": "",
                    "shell_angular_momentum": [
                        1
                    ],
                    "shell_exponents": [
                        "44.3555",
                        "10.0820",
                        "2.99590",
                        "0.93830"
                    ],
                    "shell_coefficients": [
                        [
                            "0.020868",
                            "0.130092",
                            "0.396219",
                            "0.620368"
                        ]
                    ]
                },
                {
                    "shell_function_type": "gto",
                    "shell_harmonic_type": "spherical",
                    "shell_region": "",
                    "shell_angular_momentum": [
                        1
                    ],
                    "shell_exponents": [
                        "0.2733"
                    ],
                    "shell_coefficients": [
                        [
                            "1.000000"
                        ]
                    ]
                },
                {
                    "shell_function_type": "gto",
                    "shell_harmonic_type": "spherical",
                    "shell_region": "",
                    "shell_angular_momentum": [
                        1
                    ],
                    "shell_exponents": [
                        "0.0828"
                    ],
                    "shell_coefficients": [
                        [
                            "1.000000"
                        ]
                    ]
                },
                {
                    "shell_function_type": "gto",
                    "shell_harmonic_type": "spherical",
                    "shell_region": "",
                    "shell_angular_momentum": [
                        2
                    ],
                    "shell_exponents": [
                        "0.66500"
                    ],
                    "shell_coefficients": [
                        [
                            "1.000000"
                        ]
                    ]
                },
                {
                    "shell_function_type": "gto",
                    "shell_harmonic_type": "spherical",
                    "shell_region": "",
                    "shell_angular_momentum": [
                        2
                    ],
                    "shell_exponents": [
                        "2.66000"
                    ],
                    "shell_coefficients": [
                        [
                            "1.000000"
                        ]
                    ]
                }
            ]
        }
    }
}