{
  "molssi_bse_schema": {
    "schema_type": "element",
    "schema_version": "0.1"
  },
  "name": "DZP + Diffuse (Dunning)",
  "description": "DZPD    Double Zeta + Polarization + Diffuse",
  "elements": {
    "1": {
      "components": [
        "DUNNINGDZ.0.json",
        "DUNHAYPOL_noref.json",
        "DUNHAYDIF_DUNHAYDIF-BS-REF.json"
      ]
    },
    "3": {
      "components": [
        "DUNNINGDZ.0.json",
        "DUNHAYPOL_noref.json",
        "DUNHAYDIF_DUNHAYDIF-BS-REF.json"
      ]
    },
    "5": {
      "components": [
        "DUNNINGDZ.0.json",
        "DUNHAYPOL_noref.json",
        "DUNHAYDIF_DUNHAYDIF-BS-REF.json"
      ]
    },
    "6": {
      "components": [
        "DUNNINGDZ.0.json",
        "DUNHAYPOL_noref.json",
        "DUNHAYDIF_DUNHAYDIF-BS-REF.json"
      ]
    },
    "7": {
      "components": [
        "DUNNINGDZ.0.json",
        "DUNHAYPOL_noref.json",
        "DUNHAYDIF_DUNHAYDIF-BS-REF.json"
      ]
    },
    "8": {
      "components": [
        "DUNNINGDZ.0.json",
        "DUNHAYPOL_noref.json",
        "DUNHAYDIF_DUNHAYDIF-BS-REF.json"
      ]
    },
    "9": {
      "components": [
        "DUNNINGDZ.0.json",
        "DUNHAYPOL_noref.json",
        "DUNHAYDIF_DUNHAYDIF-BS-REF.json"
      ]
    },
    "10": {
      "components": [
        "DUNNINGDZ.0.json",
        "DUNHAYPOL_noref.json",
        "DUNHAYDIF_DUNHAYDIF-BS-REF.json"
      ]
    }
  }
}