{
  "molssi_bse_schema": {
    "schema_type": "table",
    "schema_version": "0.1"
  },
  "revision_description": "Data from the original Basis Set Exchange",
  "elements": {
    "1": "G3LARGEXP.0.element.json",
    "2": "G3LARGEXP.0.element.json",
    "3": "G3LARGEXP.0.element.json",
    "4": "G3LARGEXP.0.element.json",
    "5": "G3LARGEXP.0.element.json",
    "6": "G3LARGEXP.0.element.json",
    "7": "G3LARGEXP.0.element.json",
    "8": "G3LARGEXP.0.element.json",
    "9": "G3LARGEXP.0.element.json",
    "10": "G3LARGEXP.0.element.json",
    "11": "G3LARGEXP.0.element.json",
    "12": "G3LARGEXP.0.element.json",
    "13": "G3LARGEXP.0.element.json",
    "14": "G3LARGEXP.0.element.json",
    "15": "G3LARGEXP.0.element.json",
    "16": "G3LARGEXP.0.element.json",
    "17": "G3LARGEXP.0.element.json",
    "18": "G3LARGEXP.0.element.json",
    "19": "G3LARGEXP.0.element.json",
    "20": "G3LARGEXP.0.element.json",
    "21": "G3LARGEXP.0.element.json",
    "22": "G3LARGEXP.0.element.json",
    "23": "G3LARGEXP.0.element.json",
    "24": "G3LARGEXP.0.element.json",
    "25": "G3LARGEXP.0.element.json",
    "26": "G3LARGEXP.0.element.json",
    "27": "G3LARGEXP.0.element.json",
    "28": "G3LARGEXP.0.element.json",
    "29": "G3LARGEXP.0.element.json",
    "30": "G3LARGEXP.0.element.json",
    "31": "G3LARGEXP.0.element.json",
    "32": "G3LARGEXP.0.element.json",
    "33": "G3LARGEXP.0.element.json",
    "34": "G3LARGEXP.0.element.json",
    "35": "G3LARGEXP.0.element.json",
    "36": "G3LARGEXP.0.element.json"
  }
}